pyucell/__init__.py
pyucell/knn.py
pyucell/ranks.py
pyucell/scoring.py
pyucell-0.5.0.dist-info/METADATA
pyucell-0.5.0.dist-info/WHEEL
pyucell-0.5.0.dist-info/licenses/LICENSE
pyucell-0.5.0.dist-info/RECORD
